website_dorker_pro/__init__.py
website_dorker_pro/cli.py
website_dorker_pro/main.py
website_dorker_pro-2.1.0.dist-info/licenses/LICENSE
website_dorker_pro-2.1.0.dist-info/METADATA
website_dorker_pro-2.1.0.dist-info/WHEEL
website_dorker_pro-2.1.0.dist-info/entry_points.txt
website_dorker_pro-2.1.0.dist-info/top_level.txt
website_dorker_pro-2.1.0.dist-info/RECORD
