Metadata-Version: 2.4
Name: website-dorker-pro
Version: 2.1.0
Summary: Website Reconnaissance Toolkit for Bug Hunters and Pentesters
Home-page: https://github.com/ZishanAdThandar/WebsiteDorkerPro
Author: Zishan Ahamed Thandar
License: MIT
Project-URL: Homepage, https://github.com/ZishanAdThandar/WebsiteDorkerPro
Project-URL: Documentation, https://github.com/ZishanAdThandar/WebsiteDorkerPro
Project-URL: Source, https://github.com/ZishanAdThandar/WebsiteDorkerPro
Project-URL: Tracker, https://github.com/ZishanAdThandar/WebsiteDorkerPro/issues
Keywords: bug-bounty,reconnaissance,penetration-testing,security,dorking,osint
Classifier: Development Status :: 4 - Beta
Classifier: Intended Audience :: Information Technology
Classifier: Topic :: Security
Classifier: License :: OSI Approved :: MIT License
Classifier: Programming Language :: Python :: 3
Classifier: Programming Language :: Python :: 3.7
Classifier: Programming Language :: Python :: 3.8
Classifier: Programming Language :: Python :: 3.9
Classifier: Programming Language :: Python :: 3.10
Classifier: Programming Language :: Python :: 3.11
Classifier: Operating System :: OS Independent
Requires-Python: >=3.7
License-File: LICENSE
Dynamic: home-page
Dynamic: license-file
Dynamic: requires-python
